{
  "annotations": {
    "list": [
      {
        "builtIn": 1,
        "datasource": "-- Grafana --",
        "enable": true,
        "hide": true,
        "iconColor": "rgba(0, 211, 255, 1)",
        "name": "Annotations & Alerts",
        "type": "dashboard"
      }
    ]
  },
  "editable": true,
  "gnetId": null,
  "graphTooltip": 0,
  "id": null,
  "links": [],
  "panels": [
    {
      "collapsed": false,
      "datasource": null,
      "gridPos": {
        "h": 1,
        "w": 24,
        "x": 0,
        "y": 0
      },
      "id": 27,
      "panels": [],
      "title": "클라우드 센터 알람",
      "type": "row"
    },
    {
      "alert": {
        "alertRuleTags": {},
        "conditions": [
          {
            "evaluator": {
              "params": [
                75
              ],
              "type": "gt"
            },
            "operator": {
              "type": "and"
            },
            "query": {
              "params": [
                "A",
                "5m",
                "now"
              ]
            },
            "reducer": {
              "params": [],
              "type": "avg"
            },
            "type": "query"
          }
        ],
        "executionErrorState": "alerting",
        "for": "5m",
        "frequency": "1m",
        "handler": 1,
        "name": "CPU 사용현황 alert",
        "noDataState": "no_data",
        "notifications": [
          {
            "uid": "ablestack-admin"
          }
        ]
      },
      "aliasColors": {},
      "bars": false,
      "dashLength": 10,
      "dashes": false,
      "datasource": "Wall",
      "description": "",
      "fieldConfig": {
        "defaults": {
          "unit": "percent"
        },
        "overrides": []
      },
      "fill": 1,
      "fillGradient": 0,
      "gridPos": {
        "h": 4,
        "w": 3,
        "x": 0,
        "y": 1
      },
      "hiddenSeries": false,
      "id": 28,
      "legend": {
        "alignAsTable": false,
        "avg": false,
        "current": false,
        "max": false,
        "min": false,
        "show": false,
        "total": false,
        "values": false
      },
      "lines": true,
      "linewidth": 1,
      "nullPointMode": "null",
      "options": {
        "alertThreshold": true
      },
      "percentage": false,
      "pluginVersion": "8.0.4",
      "pointradius": 2,
      "points": false,
      "renderer": "flot",
      "seriesOverrides": [],
      "spaceLength": 10,
      "stack": false,
      "steppedLine": false,
      "targets": [
        {
          "exemplar": true,
          "expr": "(100 - (avg by (instance) (rate(node_cpu_seconds_total{mode=\"idle\",job=\"ccvm\"}[1m])) * 100)) / on (instance) group_left (nodename) node_uname_info{}",
          "hide": false,
          "interval": "",
          "legendFormat": "{{nodename}}",
          "refId": "A"
        }
      ],
      "thresholds": [
        {
          "colorMode": "critical",
          "fill": true,
          "line": true,
          "op": "gt",
          "value": 75,
          "visible": true
        }
      ],
      "timeFrom": null,
      "timeRegions": [],
      "timeShift": null,
      "title": "CPU 사용현황",
      "tooltip": {
        "shared": true,
        "sort": 2,
        "value_type": "individual"
      },
      "transformations": [],
      "type": "graph",
      "xaxis": {
        "buckets": null,
        "mode": "time",
        "name": null,
        "show": true,
        "values": []
      },
      "yaxes": [
        {
          "$$hashKey": "object:1571",
          "format": "percent",
          "label": null,
          "logBase": 1,
          "max": "100",
          "min": "0",
          "show": true
        },
        {
          "$$hashKey": "object:1572",
          "format": "short",
          "label": null,
          "logBase": 1,
          "max": null,
          "min": null,
          "show": true
        }
      ],
      "yaxis": {
        "align": false,
        "alignLevel": null
      }
    },
    {
      "alert": {
        "alertRuleTags": {},
        "conditions": [
          {
            "evaluator": {
              "params": [
                75
              ],
              "type": "gt"
            },
            "operator": {
              "type": "and"
            },
            "query": {
              "params": [
                "A",
                "5m",
                "now"
              ]
            },
            "reducer": {
              "params": [],
              "type": "avg"
            },
            "type": "query"
          }
        ],
        "executionErrorState": "alerting",
        "for": "5m",
        "frequency": "1m",
        "handler": 1,
        "name": "메모리 사용률 alert",
        "noDataState": "no_data",
        "notifications": [
          {
            "uid": "ablestack-admin"
          }
        ]
      },
      "aliasColors": {},
      "bars": false,
      "dashLength": 10,
      "dashes": false,
      "datasource": "Wall",
      "description": "",
      "fieldConfig": {
        "defaults": {
          "unit": "percent"
        },
        "overrides": []
      },
      "fill": 1,
      "fillGradient": 0,
      "gridPos": {
        "h": 4,
        "w": 3,
        "x": 3,
        "y": 1
      },
      "hiddenSeries": false,
      "id": 29,
      "legend": {
        "alignAsTable": false,
        "avg": false,
        "current": false,
        "max": false,
        "min": false,
        "show": false,
        "total": false,
        "values": false
      },
      "lines": true,
      "linewidth": 1,
      "nullPointMode": "null",
      "options": {
        "alertThreshold": true
      },
      "percentage": false,
      "pluginVersion": "8.0.4",
      "pointradius": 2,
      "points": false,
      "renderer": "flot",
      "seriesOverrides": [],
      "spaceLength": 10,
      "stack": false,
      "steppedLine": false,
      "targets": [
        {
          "exemplar": true,
          "expr": "100 - ((node_memory_MemAvailable_bytes{job=\"ccvm\"} * 100) / node_memory_MemTotal_bytes{job=\"ccvm\"}) / on (instance) group_left (nodename) node_uname_info{}",
          "interval": "",
          "legendFormat": "{{nodename}}",
          "refId": "A"
        }
      ],
      "thresholds": [
        {
          "colorMode": "critical",
          "fill": true,
          "line": true,
          "op": "gt",
          "value": 75,
          "visible": true
        }
      ],
      "timeFrom": null,
      "timeRegions": [],
      "timeShift": null,
      "title": "메모리 사용률",
      "tooltip": {
        "shared": true,
        "sort": 2,
        "value_type": "individual"
      },
      "transformations": [],
      "type": "graph",
      "xaxis": {
        "buckets": null,
        "mode": "time",
        "name": null,
        "show": true,
        "values": []
      },
      "yaxes": [
        {
          "$$hashKey": "object:1978",
          "format": "percent",
          "label": null,
          "logBase": 1,
          "max": "100",
          "min": "0",
          "show": true
        },
        {
          "$$hashKey": "object:1979",
          "format": "short",
          "label": null,
          "logBase": 1,
          "max": null,
          "min": null,
          "show": true
        }
      ],
      "yaxis": {
        "align": false,
        "alignLevel": null
      }
    },
    {
      "alert": {
        "alertRuleTags": {},
        "conditions": [
          {
            "evaluator": {
              "params": [
                10000000
              ],
              "type": "gt"
            },
            "operator": {
              "type": "and"
            },
            "query": {
              "params": [
                "A",
                "5m",
                "now"
              ]
            },
            "reducer": {
              "params": [],
              "type": "avg"
            },
            "type": "query"
          }
        ],
        "executionErrorState": "alerting",
        "for": "5m",
        "frequency": "1m",
        "handler": 1,
        "name": "네트워크  트래픽 alert",
        "noDataState": "no_data",
        "notifications": [
          {
            "uid": "ablestack-admin"
          }
        ]
      },
      "aliasColors": {},
      "bars": false,
      "dashLength": 10,
      "dashes": false,
      "datasource": "Wall",
      "fieldConfig": {
        "defaults": {
          "unit": "binBps"
        },
        "overrides": []
      },
      "fill": 1,
      "fillGradient": 0,
      "gridPos": {
        "h": 4,
        "w": 3,
        "x": 6,
        "y": 1
      },
      "hiddenSeries": false,
      "id": 53,
      "legend": {
        "alignAsTable": false,
        "avg": false,
        "current": false,
        "max": false,
        "min": false,
        "show": false,
        "total": false,
        "values": false
      },
      "lines": true,
      "linewidth": 1,
      "nullPointMode": "null",
      "options": {
        "alertThreshold": true
      },
      "percentage": false,
      "pluginVersion": "8.0.4",
      "pointradius": 2,
      "points": false,
      "renderer": "flot",
      "seriesOverrides": [],
      "spaceLength": 10,
      "stack": false,
      "steppedLine": false,
      "targets": [
        {
          "exemplar": true,
          "expr": "((sum by(instance) (\n  (\n  irate(node_network_receive_bytes_total{job=\"ccvm\",device!=\"lo\"}[1m])\n  ) +\n  (\n  irate(node_network_transmit_bytes_total{job=\"ccvm\",device!=\"lo\"}[1m])\n  ))\n  )\n  / on (instance) group_left (nodename) node_uname_info{}\n)",
          "hide": false,
          "interval": "",
          "legendFormat": "{{nodename}}",
          "refId": "A"
        }
      ],
      "thresholds": [
        {
          "colorMode": "critical",
          "fill": true,
          "line": true,
          "op": "gt",
          "value": 10000000,
          "visible": true
        }
      ],
      "timeFrom": null,
      "timeRegions": [],
      "timeShift": null,
      "title": "네트워크  트래픽",
      "tooltip": {
        "shared": true,
        "sort": 2,
        "value_type": "individual"
      },
      "type": "graph",
      "xaxis": {
        "buckets": null,
        "mode": "time",
        "name": null,
        "show": true,
        "values": []
      },
      "yaxes": [
        {
          "$$hashKey": "object:2228",
          "format": "binBps",
          "label": null,
          "logBase": 1,
          "max": null,
          "min": null,
          "show": true
        },
        {
          "$$hashKey": "object:2229",
          "format": "short",
          "label": null,
          "logBase": 1,
          "max": null,
          "min": null,
          "show": true
        }
      ],
      "yaxis": {
        "align": false,
        "alignLevel": null
      }
    },
    {
      "alert": {
        "alertRuleTags": {},
        "conditions": [
          {
            "evaluator": {
              "params": [
                0.1
              ],
              "type": "gt"
            },
            "operator": {
              "type": "and"
            },
            "query": {
              "params": [
                "A",
                "5m",
                "now"
              ]
            },
            "reducer": {
              "params": [],
              "type": "avg"
            },
            "type": "query"
          }
        ],
        "executionErrorState": "alerting",
        "for": "5m",
        "frequency": "1m",
        "handler": 1,
        "name": "디스크 읽기 지연 alert",
        "noDataState": "no_data",
        "notifications": [
          {
            "uid": "ablestack-admin"
          }
        ]
      },
      "aliasColors": {},
      "bars": false,
      "dashLength": 10,
      "dashes": false,
      "datasource": "Wall",
      "fill": 1,
      "fillGradient": 0,
      "gridPos": {
        "h": 4,
        "w": 3,
        "x": 9,
        "y": 1
      },
      "hiddenSeries": false,
      "id": 51,
      "legend": {
        "avg": false,
        "current": false,
        "hideEmpty": false,
        "hideZero": false,
        "max": false,
        "min": false,
        "show": false,
        "total": false,
        "values": false
      },
      "lines": true,
      "linewidth": 1,
      "nullPointMode": "null",
      "options": {
        "alertThreshold": true
      },
      "percentage": false,
      "pluginVersion": "8.0.4",
      "pointradius": 2,
      "points": false,
      "renderer": "flot",
      "seriesOverrides": [],
      "spaceLength": 10,
      "stack": false,
      "steppedLine": false,
      "targets": [
        {
          "exemplar": true,
          "expr": "rate(node_disk_read_time_seconds_total{job=\"ccvm\"}[1m]) / rate(node_disk_reads_completed_total{job=\"ccvm\"}[1m])",
          "interval": "",
          "legendFormat": "{{instance}}-{{device}}",
          "refId": "A"
        }
      ],
      "thresholds": [
        {
          "colorMode": "critical",
          "fill": true,
          "line": true,
          "op": "gt",
          "value": 0.1,
          "visible": true
        }
      ],
      "timeFrom": null,
      "timeRegions": [
        {
          "$$hashKey": "object:8108",
          "colorMode": "background6",
          "fill": true,
          "fillColor": "rgba(234, 112, 112, 0.12)",
          "line": false,
          "lineColor": "rgba(237, 46, 24, 0.60)",
          "op": "time"
        }
      ],
      "timeShift": null,
      "title": "디스크 읽기 지연",
      "tooltip": {
        "shared": true,
        "sort": 0,
        "value_type": "individual"
      },
      "type": "graph",
      "xaxis": {
        "buckets": null,
        "mode": "time",
        "name": null,
        "show": true,
        "values": []
      },
      "yaxes": [
        {
          "$$hashKey": "object:4081",
          "format": "s",
          "label": null,
          "logBase": 1,
          "max": null,
          "min": null,
          "show": true
        },
        {
          "$$hashKey": "object:4082",
          "format": "short",
          "label": null,
          "logBase": 1,
          "max": null,
          "min": null,
          "show": false
        }
      ],
      "yaxis": {
        "align": false,
        "alignLevel": null
      }
    },
    {
      "alert": {
        "alertRuleTags": {},
        "conditions": [
          {
            "evaluator": {
              "params": [
                0.1
              ],
              "type": "gt"
            },
            "operator": {
              "type": "and"
            },
            "query": {
              "params": [
                "A",
                "5m",
                "now"
              ]
            },
            "reducer": {
              "params": [],
              "type": "avg"
            },
            "type": "query"
          }
        ],
        "executionErrorState": "alerting",
        "for": "5m",
        "frequency": "1m",
        "handler": 1,
        "name": "디스크 쓰기 지연 alert",
        "noDataState": "no_data",
        "notifications": [
          {
            "uid": "ablestack-admin"
          }
        ]
      },
      "aliasColors": {},
      "bars": false,
      "dashLength": 10,
      "dashes": false,
      "datasource": "Wall",
      "fill": 1,
      "fillGradient": 0,
      "gridPos": {
        "h": 4,
        "w": 3,
        "x": 12,
        "y": 1
      },
      "hiddenSeries": false,
      "id": 52,
      "legend": {
        "avg": false,
        "current": false,
        "max": false,
        "min": false,
        "show": false,
        "total": false,
        "values": false
      },
      "lines": true,
      "linewidth": 1,
      "nullPointMode": "null",
      "options": {
        "alertThreshold": true
      },
      "percentage": false,
      "pluginVersion": "8.0.4",
      "pointradius": 2,
      "points": false,
      "renderer": "flot",
      "seriesOverrides": [],
      "spaceLength": 10,
      "stack": false,
      "steppedLine": false,
      "targets": [
        {
          "exemplar": true,
          "expr": "rate(node_disk_write_time_seconds_total{job=\"ccvm\"}[1m]) / rate(node_disk_writes_completed_total{job=\"ccvm\"}[1m])",
          "interval": "",
          "legendFormat": "{{instance}}-{{device}}",
          "refId": "A"
        }
      ],
      "thresholds": [
        {
          "colorMode": "critical",
          "fill": true,
          "line": true,
          "op": "gt",
          "value": 0.1,
          "visible": true
        }
      ],
      "timeFrom": null,
      "timeRegions": [],
      "timeShift": null,
      "title": "디스크 쓰기 지연",
      "tooltip": {
        "shared": true,
        "sort": 0,
        "value_type": "individual"
      },
      "type": "graph",
      "xaxis": {
        "buckets": null,
        "mode": "time",
        "name": null,
        "show": true,
        "values": []
      },
      "yaxes": [
        {
          "$$hashKey": "object:4081",
          "format": "s",
          "label": null,
          "logBase": 1,
          "max": null,
          "min": null,
          "show": true
        },
        {
          "$$hashKey": "object:4082",
          "format": "short",
          "label": null,
          "logBase": 1,
          "max": null,
          "min": null,
          "show": true
        }
      ],
      "yaxis": {
        "align": false,
        "alignLevel": null
      }
    },
    {
      "alert": {
        "alertRuleTags": {},
        "conditions": [
          {
            "evaluator": {
              "params": [
                75
              ],
              "type": "gt"
            },
            "operator": {
              "type": "and"
            },
            "query": {
              "params": [
                "A",
                "5m",
                "now"
              ]
            },
            "reducer": {
              "params": [],
              "type": "avg"
            },
            "type": "query"
          }
        ],
        "executionErrorState": "alerting",
        "for": "5m",
        "frequency": "1m",
        "handler": 1,
        "name": "Root 디스크 사용률 alert",
        "noDataState": "no_data",
        "notifications": [
          {
            "uid": "ablestack-admin"
          }
        ]
      },
      "aliasColors": {},
      "bars": false,
      "dashLength": 10,
      "dashes": false,
      "datasource": "Wall",
      "fill": 1,
      "fillGradient": 0,
      "gridPos": {
        "h": 4,
        "w": 3,
        "x": 15,
        "y": 1
      },
      "hiddenSeries": false,
      "id": 41,
      "legend": {
        "avg": false,
        "current": false,
        "max": false,
        "min": false,
        "show": false,
        "total": false,
        "values": false
      },
      "lines": true,
      "linewidth": 1,
      "nullPointMode": "null",
      "options": {
        "alertThreshold": true
      },
      "percentage": false,
      "pluginVersion": "8.0.4",
      "pointradius": 2,
      "points": false,
      "renderer": "flot",
      "seriesOverrides": [],
      "spaceLength": 10,
      "stack": false,
      "steppedLine": false,
      "targets": [
        {
          "exemplar": true,
          "expr": "100 - ((node_filesystem_avail_bytes{mountpoint=\"/\",fstype!=\"rootfs\", job=\"ccvm\"} * 100) / node_filesystem_size_bytes{mountpoint=\"/\",fstype!=\"rootfs\", job=\"ccvm\"}) / on (instance) group_left (nodename) node_uname_info{}",
          "interval": "",
          "legendFormat": "{{nodename}}",
          "refId": "A"
        }
      ],
      "thresholds": [
        {
          "colorMode": "critical",
          "fill": true,
          "line": true,
          "op": "gt",
          "value": 75,
          "visible": true
        }
      ],
      "timeFrom": null,
      "timeRegions": [],
      "timeShift": null,
      "title": "Root 디스크 사용률",
      "tooltip": {
        "shared": true,
        "sort": 0,
        "value_type": "individual"
      },
      "type": "graph",
      "xaxis": {
        "buckets": null,
        "mode": "time",
        "name": null,
        "show": true,
        "values": []
      },
      "yaxes": [
        {
          "$$hashKey": "object:2000",
          "decimals": 0,
          "format": "percent",
          "label": null,
          "logBase": 1,
          "max": null,
          "min": null,
          "show": true
        },
        {
          "$$hashKey": "object:2001",
          "format": "short",
          "label": null,
          "logBase": 1,
          "max": null,
          "min": null,
          "show": true
        }
      ],
      "yaxis": {
        "align": false,
        "alignLevel": null
      }
    },
    {
      "alert": {
        "alertRuleTags": {},
        "conditions": [
          {
            "evaluator": {
              "params": [
                1
              ],
              "type": "lt"
            },
            "operator": {
              "type": "and"
            },
            "query": {
              "params": [
                "A",
                "5m",
                "now"
              ]
            },
            "reducer": {
              "params": [],
              "type": "avg"
            },
            "type": "query"
          }
        ],
        "executionErrorState": "alerting",
        "for": "5m",
        "frequency": "1m",
        "handler": 1,
        "name": "Mold 상태 alert",
        "noDataState": "no_data",
        "notifications": [
          {
            "uid": "ablestack-admin"
          }
        ]
      },
      "aliasColors": {},
      "bars": false,
      "dashLength": 10,
      "dashes": false,
      "datasource": "Wall",
      "description": "",
      "fill": 1,
      "fillGradient": 0,
      "gridPos": {
        "h": 4,
        "w": 3,
        "x": 0,
        "y": 5
      },
      "hiddenSeries": false,
      "id": 68,
      "legend": {
        "avg": false,
        "current": false,
        "hideEmpty": false,
        "hideZero": false,
        "max": false,
        "min": false,
        "show": false,
        "total": false,
        "values": false
      },
      "lines": true,
      "linewidth": 1,
      "nullPointMode": "null",
      "options": {
        "alertThreshold": true
      },
      "percentage": false,
      "pluginVersion": "8.0.4",
      "pointradius": 2,
      "points": false,
      "renderer": "flot",
      "seriesOverrides": [],
      "spaceLength": 10,
      "stack": false,
      "steppedLine": false,
      "targets": [
        {
          "exemplar": true,
          "expr": "label_replace(\n(\n  probe_success{pingip=~\".*:8080\"}\n),\n \"pingip\",\n \"$1\",\n \"pingip\",\n \"(.*):.*\"\n)\n/ on (pingip) group_left() probe_success{pingip=~\".*\", job=\"ccvm-blackbox\"}",
          "format": "time_series",
          "hide": false,
          "instant": false,
          "interval": "",
          "intervalFactor": 1,
          "legendFormat": "{{pingip}}",
          "refId": "A"
        }
      ],
      "thresholds": [
        {
          "colorMode": "critical",
          "fill": true,
          "line": true,
          "op": "lt",
          "value": 1,
          "visible": true
        }
      ],
      "timeFrom": null,
      "timeRegions": [],
      "timeShift": null,
      "title": "Mold 상태",
      "tooltip": {
        "shared": true,
        "sort": 0,
        "value_type": "individual"
      },
      "type": "graph",
      "xaxis": {
        "buckets": null,
        "mode": "time",
        "name": null,
        "show": true,
        "values": []
      },
      "yaxes": [
        {
          "$$hashKey": "object:1706",
          "decimals": 0,
          "format": "short",
          "label": "",
          "logBase": 1,
          "max": "1",
          "min": "0",
          "show": true
        },
        {
          "$$hashKey": "object:1707",
          "format": "short",
          "label": null,
          "logBase": 1,
          "max": null,
          "min": null,
          "show": true
        }
      ],
      "yaxis": {
        "align": false,
        "alignLevel": null
      }
    },
    {
      "alert": {
        "alertRuleTags": {},
        "conditions": [
          {
            "evaluator": {
              "params": [
                1
              ],
              "type": "lt"
            },
            "operator": {
              "type": "and"
            },
            "query": {
              "params": [
                "A",
                "5m",
                "now"
              ]
            },
            "reducer": {
              "params": [],
              "type": "avg"
            },
            "type": "query"
          }
        ],
        "executionErrorState": "alerting",
        "for": "5m",
        "frequency": "1m",
        "handler": 1,
        "name": "호스트 수집기 alert",
        "noDataState": "no_data",
        "notifications": [
          {
            "uid": "ablestack-admin"
          }
        ]
      },
      "aliasColors": {},
      "bars": false,
      "dashLength": 10,
      "dashes": false,
      "datasource": "Wall",
      "fill": 1,
      "fillGradient": 0,
      "gridPos": {
        "h": 4,
        "w": 3,
        "x": 3,
        "y": 5
      },
      "hiddenSeries": false,
      "id": 69,
      "legend": {
        "avg": false,
        "current": false,
        "max": false,
        "min": false,
        "show": false,
        "total": false,
        "values": false
      },
      "lines": true,
      "linewidth": 1,
      "nullPointMode": "null",
      "options": {
        "alertThreshold": true
      },
      "percentage": false,
      "pluginVersion": "8.0.4",
      "pointradius": 2,
      "points": false,
      "renderer": "flot",
      "seriesOverrides": [],
      "spaceLength": 10,
      "stack": false,
      "steppedLine": false,
      "targets": [
        {
          "exemplar": true,
          "expr": "label_replace(\n(\n sum by (instance)\n  (namedprocess_namegroup_states{instance=~\".*:9256\", job=\"ccvm-process-exporter\", matches=\"map[:node_exporter]\"})\n),\n \"pingip\",\n \"$1\",\n \"instance\",\n \"(.*):.*\"\n)\n/ on (pingip) group_left() probe_success{pingip=~\".*\", job=\"ccvm-blackbox\"}",
          "format": "time_series",
          "hide": false,
          "instant": false,
          "interval": "",
          "legendFormat": "{{instance}}",
          "refId": "A"
        }
      ],
      "thresholds": [
        {
          "colorMode": "critical",
          "fill": true,
          "line": true,
          "op": "lt",
          "value": 1,
          "visible": true
        }
      ],
      "timeFrom": null,
      "timeRegions": [],
      "timeShift": null,
      "title": "호스트 수집기",
      "tooltip": {
        "shared": true,
        "sort": 0,
        "value_type": "individual"
      },
      "transformations": [],
      "type": "graph",
      "xaxis": {
        "buckets": null,
        "mode": "time",
        "name": null,
        "show": true,
        "values": []
      },
      "yaxes": [
        {
          "$$hashKey": "object:647",
          "format": "short",
          "label": null,
          "logBase": 1,
          "max": null,
          "min": "0",
          "show": true
        },
        {
          "$$hashKey": "object:648",
          "format": "short",
          "label": null,
          "logBase": 1,
          "max": null,
          "min": null,
          "show": true
        }
      ],
      "yaxis": {
        "align": false,
        "alignLevel": null
      }
    },
    {
      "alert": {
        "alertRuleTags": {},
        "conditions": [
          {
            "evaluator": {
              "params": [
                1
              ],
              "type": "lt"
            },
            "operator": {
              "type": "and"
            },
            "query": {
              "params": [
                "A",
                "5m",
                "now"
              ]
            },
            "reducer": {
              "params": [],
              "type": "avg"
            },
            "type": "query"
          }
        ],
        "executionErrorState": "alerting",
        "for": "5m",
        "frequency": "1m",
        "handler": 1,
        "name": "프로세스 수집기 alert",
        "noDataState": "no_data",
        "notifications": [
          {
            "uid": "ablestack-admin"
          }
        ]
      },
      "aliasColors": {},
      "bars": false,
      "dashLength": 10,
      "dashes": false,
      "datasource": "Wall",
      "fill": 1,
      "fillGradient": 0,
      "gridPos": {
        "h": 4,
        "w": 3,
        "x": 6,
        "y": 5
      },
      "hiddenSeries": false,
      "id": 70,
      "legend": {
        "avg": false,
        "current": false,
        "max": false,
        "min": false,
        "show": false,
        "total": false,
        "values": false
      },
      "lines": true,
      "linewidth": 1,
      "nullPointMode": "null",
      "options": {
        "alertThreshold": true
      },
      "percentage": false,
      "pluginVersion": "8.0.4",
      "pointradius": 2,
      "points": false,
      "renderer": "flot",
      "seriesOverrides": [],
      "spaceLength": 10,
      "stack": false,
      "steppedLine": false,
      "targets": [
        {
          "exemplar": true,
          "expr": "label_replace(\n(\n sum by (instance)\n  (namedprocess_namegroup_states{instance=~\".*:9256\", job=\"ccvm-process-exporter\", matches=\"map[:process-exporter]\"})\n),\n \"pingip\",\n \"$1\",\n \"instance\",\n \"(.*):.*\"\n)\n/ on (pingip) group_left() probe_success{pingip=~\".*\", job=\"ccvm-blackbox\"}",
          "format": "time_series",
          "hide": false,
          "instant": false,
          "interval": "",
          "legendFormat": "{{instance}}",
          "refId": "A"
        }
      ],
      "thresholds": [
        {
          "colorMode": "critical",
          "fill": true,
          "line": true,
          "op": "lt",
          "value": 1,
          "visible": true
        }
      ],
      "timeFrom": null,
      "timeRegions": [],
      "timeShift": null,
      "title": "프로세스 수집기",
      "tooltip": {
        "shared": true,
        "sort": 0,
        "value_type": "individual"
      },
      "transformations": [],
      "type": "graph",
      "xaxis": {
        "buckets": null,
        "mode": "time",
        "name": null,
        "show": true,
        "values": []
      },
      "yaxes": [
        {
          "$$hashKey": "object:647",
          "format": "short",
          "label": null,
          "logBase": 1,
          "max": null,
          "min": "0",
          "show": true
        },
        {
          "$$hashKey": "object:648",
          "format": "short",
          "label": null,
          "logBase": 1,
          "max": null,
          "min": null,
          "show": true
        }
      ],
      "yaxis": {
        "align": false,
        "alignLevel": null
      }
    },
    {
      "alert": {
        "alertRuleTags": {},
        "conditions": [
          {
            "evaluator": {
              "params": [
                1
              ],
              "type": "lt"
            },
            "operator": {
              "type": "and"
            },
            "query": {
              "params": [
                "A",
                "5m",
                "now"
              ]
            },
            "reducer": {
              "params": [],
              "type": "avg"
            },
            "type": "query"
          }
        ],
        "executionErrorState": "alerting",
        "for": "5m",
        "frequency": "1m",
        "handler": 1,
        "name": "가동 상태 alert",
        "noDataState": "no_data",
        "notifications": [
          {
            "uid": "ablestack-admin"
          }
        ]
      },
      "aliasColors": {},
      "bars": false,
      "dashLength": 10,
      "dashes": false,
      "datasource": "Wall",
      "description": "",
      "fill": 1,
      "fillGradient": 0,
      "gridPos": {
        "h": 4,
        "w": 3,
        "x": 0,
        "y": 9
      },
      "hiddenSeries": false,
      "id": 75,
      "legend": {
        "avg": false,
        "current": false,
        "hideEmpty": false,
        "hideZero": false,
        "max": false,
        "min": false,
        "show": false,
        "total": false,
        "values": false
      },
      "lines": true,
      "linewidth": 1,
      "nullPointMode": "null",
      "options": {
        "alertThreshold": true
      },
      "percentage": false,
      "pluginVersion": "8.0.4",
      "pointradius": 2,
      "points": false,
      "renderer": "flot",
      "seriesOverrides": [],
      "spaceLength": 10,
      "stack": false,
      "steppedLine": false,
      "targets": [
        {
          "exemplar": true,
          "expr": "probe_success{pingip=~\".*\", job=\"ccvm-blackbox\"}",
          "format": "time_series",
          "hide": false,
          "instant": false,
          "interval": "",
          "intervalFactor": 1,
          "legendFormat": "{{pingip}}",
          "refId": "A"
        }
      ],
      "thresholds": [
        {
          "colorMode": "critical",
          "fill": true,
          "line": true,
          "op": "lt",
          "value": 1,
          "visible": true
        }
      ],
      "timeFrom": null,
      "timeRegions": [],
      "timeShift": null,
      "title": "가동 상태",
      "tooltip": {
        "shared": true,
        "sort": 0,
        "value_type": "individual"
      },
      "type": "graph",
      "xaxis": {
        "buckets": null,
        "mode": "time",
        "name": null,
        "show": true,
        "values": []
      },
      "yaxes": [
        {
          "$$hashKey": "object:1706",
          "decimals": 0,
          "format": "short",
          "label": "",
          "logBase": 1,
          "max": "1",
          "min": "0",
          "show": true
        },
        {
          "$$hashKey": "object:1707",
          "format": "short",
          "label": null,
          "logBase": 1,
          "max": null,
          "min": null,
          "show": true
        }
      ],
      "yaxis": {
        "align": false,
        "alignLevel": null
      }
    }
  ],
  "refresh": "10s",
  "schemaVersion": 30,
  "style": "dark",
  "tags": [],
  "templating": {
    "list": []
  },
  "time": {
    "from": "now-1h",
    "to": "now"
  },
  "timepicker": {},
  "timezone": "",
  "title": "클라우드 센터 알람 대시보드",
  "uid": "ccvm_alert",
  "version": 1
}
